[
    {
      "name": "Gigi’s Viewing Party",
      "date": "2025-08-07",
      "city": "Paris",
      "venueName": "TiTi Palacio",
      "address": "17 Boulevard Morland, 75004 Paris, France",
      "startDate": "2025-08-07T18:00:00",
      "endDate": "2025-08-07T20:30:00",
      "instagram": "@titi.palacio",
      "imageUrl": null,
      "description": "Cocktail‑style viewing party",
      "price": 28
    },
    {
      "name": "Peep Show Viewing Ep.5",
      "date": "2025-08-07",
      "city": "Paris",
      "venueName": "La Bellevilloise",
      "address": "19–21 Rue Boyer, 75020 Paris, France",
      "startDate": "2025-08-07T18:30:00",
      "endDate": "2025-08-08T00:30:00",
      "instagram": "@labellevilloise",
      "imageUrl": null,
      "description": "Viewing party at La Bellevilloise",
      "price": ""
    },
    {
      "name": "B.Boat Summer Cruise",
      "date": "2025-08-07",
      "city": "Paris",
      "venueName": "River's King",
      "address": "4 Quai Saint‑Bernard, 75005 Paris, France",
      "startDate": "2025-08-07T19:00:00",
      "endDate": "2025-08-08T02:00:00",
      "instagram": "",
      "imageUrl": null,
      "description": "Dating and dance‑floor boat cruise",
      "price": ""
    },
    {
      "name": "66 Hell",
      "date": "2025-08-07",
      "city": "Paris",
      "venueName": "FVTvR",
      "address": "32–34 Quai d’Austerlitz, 75013 Paris, France",
      "startDate": "2025-08-07T23:00:00",
      "endDate": "2025-08-08T06:00:00",
      "instagram": "",
      "imageUrl": null,
      "description": "Acid techno clash at FVTvR",
      "price": ""
    },
    {
      "name": "BFF‑Viewing Ep.5",
      "date": "2025-08-07",
      "city": "Paris",
      "venueName": "Raidd Bar",
      "address": "23 Rue du Temple, 75004 Paris, France",
      "startDate": "2025-08-07T18:00:00",
      "endDate": "2025-08-08T04:00:00",
      "instagram": "@raiddbar",
      "imageUrl": null,
      "description": "Pop viewing party with Shower Boy",
      "price": ""
    },
    {
      "name": "Jeudiok: S3X.A.Pill",
      "date": "2025-08-07",
      "city": "Paris",
      "venueName": "Wanderlust",
      "address": "32 Quai d’Austerlitz, 75013 Paris, France",
      "startDate": "2025-08-07T19:00:00",
      "endDate": "2025-08-08T06:00:00",
      "instagram": "",
      "imageUrl": null,
      "description": "Jeudiok party at Wanderlust",
      "price": ""
    },
    {
      "name": "Viewing Party",
      "date": "2025-08-07",
      "city": "Paris",
      "venueName": "We Are Brewers",
      "address": "16 Boulevard Jules Ferry, 75011 Paris, France",
      "startDate": "2025-08-07T19:00:00",
      "endDate": "2025-08-07T23:00:00",
      "instagram": "@wearebrewers",
      "imageUrl": null,
      "description": "Viewing party at inclusive craft‑beer taproom",
      "price": ""
    },
    {
      "name": "The House of Charli",
      "date": "2025-08-08",
      "city": "Paris",
      "venueName": "Gibus Club",
      "address": "18 Rue du Faubourg du Temple, 75011 Paris, France",
      "startDate": "2025-08-08T00:00:00",
      "endDate": "2025-08-08T06:00:00",
      "instagram": "@gibusclub",
      "imageUrl": null,
      "description": "Glam‑club night at Gibus Club",
      "price": 15
    },
    {
      "name": "ChemsPause",
      "date": "2025-08-08",
      "city": "Paris",
      "venueName": "ChemsPause",
      "address": "22 Rue Malher, 75004 Paris, France",
      "startDate": "2025-08-08T19:00:00",
      "endDate": "2025-08-08T21:30:00",
      "instagram": "",
      "imageUrl": null,
      "description": "Community gathering at ChemsPause",
      "price": ""
    },
    {
      "name": "Vendredi X sur Seine",
      "date": "2025-08-08",
      "city": "Paris",
      "venueName": "Scilicet",
      "address": "55 Quai de la Rapée, 75012 Paris, France",
      "startDate": "2025-08-08T19:00:00",
      "endDate": "2025-08-09T02:00:00",
      "instagram": "",
      "imageUrl": null,
      "description": "Boat party on the Seine",
      "price": ""
    },
    {
      "name": "Batopia X La Mona",
      "date": "2025-08-08",
      "city": "Paris",
      "venueName": "Badaboum",
      "address": "2 bis Rue des Taillandiers, 75011 Paris, France",
      "startDate": "2025-08-08T00:00:00",
      "endDate": "2025-08-09T07:00:00",
      "instagram": "@badaboum.paris",
      "imageUrl": null,
      "description": "Electro house at Badaboum",
      "price": 15
    },
    {
      "name": "Virage",
      "date": "2025-08-08",
      "city": "Paris",
      "venueName": "Virage",
      "address": "26 Rue Hélène Brion, 75013 Paris, France",
      "startDate": "2025-08-08T00:00:00",
      "endDate": "2025-08-09T07:00:00",
      "instagram": "",
      "imageUrl": null,
      "description": "Electronic dance night at Virage",
      "price": ""
    },
    {
      "name": "It’s B(ea)ch Nicki X Doechii",
      "date": "2025-08-08",
      "city": "Paris",
      "venueName": "Club La Nuit",
      "address": "8 Boulevard de la Madeleine, 75009 Paris, France",
      "startDate": "2025-08-08T00:00:00",
      "endDate": "2025-08-09T06:00:00",
      "instagram": "",
      "imageUrl": null,
      "description": "Beach‑themed pop night",
      "price": ""
    },
    {
      "name": "Scene Ouverte",
      "date": "2025-08-08",
      "city": "Paris",
      "venueName": "Cabaret des Merveilles",
      "address": "24 Rue de Lappe, 75011 Paris, France",
      "startDate": "2025-08-08T20:00:00",
      "endDate": "2025-08-08T23:00:00",
      "instagram": "",
      "imageUrl": null,
      "description": "Open‑theme arts evening",
      "price": ""
    },
    {
      "name": "TOYZ",
      "date": "2025-08-09",
      "city": "Paris",
      "venueName": "FVTvR",
      "address": "32–34 Quai d’Austerlitz, 75013 Paris, France",
      "startDate": "2025-08-09T23:00:00",
      "endDate": "2025-08-10T05:00:00",
      "instagram": "",
      "imageUrl": null,
      "description": "ETechno acid house at FVTvR",
      "price": ""
    },
    {
      "name": "Purple Legacy",
      "date": "2025-08-09",
      "city": "Paris",
      "venueName": "YOYO",
      "address": "13 Avenue du Président Wilson, 75116 Paris, France",
      "startDate": "2025-08-10T00:00:00",
      "endDate": "2025-08-10T06:00:00",
      "instagram": "",
      "imageUrl": null,
      "description": "Pop show at YOYO",
      "price": ""
    },
    {
      "name": "Gibus Summer Club",
      "date": "2025-08-09",
      "city": "Paris",
      "venueName": "Gibus Club",
      "address": "18 Rue du Faubourg du Temple, 75011 Paris, France",
      "startDate": "2025-08-10T00:00:00",
      "endDate": "2025-08-10T06:00:00",
      "instagram": "@gibusclub",
      "imageUrl": null,
      "description": "Electro‑house night at Gibus",
      "price": 15
    },
    {
      "name": "La Soirée Drôle de Dames",
      "date": "2025-08-09",
      "city": "Paris",
      "venueName": "Le Pandora",
      "address": "34 Rue Keller, 75011 Paris, France",
      "startDate": "2025-08-09T21:00:00",
      "endDate": "2025-08-10T04:00:00",
      "instagram": "",
      "imageUrl": null,
      "description": "T-girls focused party at Le Pandora",
      "price": ""
    },
    {
      "name": "BBB Nicki Club",
      "date": "2025-08-10",
      "city": "Paris",
      "venueName": "Gibus Club",
      "address": "18 Rue du Faubourg du Temple, 75011 Paris, France",
      "startDate": "2025-08-10T00:00:00",
      "endDate": "2025-08-10T06:00:00",
      "instagram": "@gibusclub",
      "imageUrl": null,
      "description": "Nicki‑inspired house night",
      "price": 15
    },
    {
      "name": "Sun/Day",
      "date": "2025-08-10",
      "city": "Paris",
      "venueName": "Virage",
      "address": "26 Rue Hélène Brion, 75013 Paris, France",
      "startDate": "2025-08-10T16:00:00",
      "endDate": "2025-08-11T01:00:00",
      "instagram": "",
      "imageUrl": null,
      "description": "Sunday house/techno/electro session",
      "price": ""
    }
  ]
  